cxx_flow/__init__.py
cxx_flow/__main__.py
cxx_flow/api/__init__.py
cxx_flow/api/arg.py
cxx_flow/api/completers.py
cxx_flow/api/ctx.py
cxx_flow/api/env.py
cxx_flow/api/init.py
cxx_flow/api/makefile.py
cxx_flow/api/step.py
cxx_flow/base/__init__.py
cxx_flow/base/cmd.py
cxx_flow/base/inspect.py
cxx_flow/base/matrix.py
cxx_flow/base/plugins.py
cxx_flow/base/uname.py
cxx_flow/flow/__init__.py
cxx_flow/flow/configs.py
cxx_flow/flow/dependency.py
cxx_flow/flow/init.py
cxx_flow/flow/interact.py
cxx_flow/flow/layer.py
cxx_flow/flow/steps.py
cxx_flow/flow/cli/__init__.py
cxx_flow/flow/cli/cmds.py
cxx_flow/flow/cli/finder.py
cxx_flow/log/__init__.py
cxx_flow/log/commit.py
cxx_flow/log/fmt.py
cxx_flow/log/format.py
cxx_flow/log/msg.py
cxx_flow/log/release.py
cxx_flow/log/hosting/__init__.py
cxx_flow/log/hosting/github.py
cxx_flow/log/rich_text/__init__.py
cxx_flow/log/rich_text/api.py
cxx_flow/log/rich_text/markdown.py
cxx_flow/log/rich_text/re_structured_text.py
cxx_flow/plugins/__init__.py
cxx_flow/plugins/base.py
cxx_flow/plugins/github.py
cxx_flow/plugins/cmake/__init__.py
cxx_flow/plugins/cmake/__version__.py
cxx_flow/plugins/cmake/build.py
cxx_flow/plugins/cmake/config.py
cxx_flow/plugins/cmake/context.py
cxx_flow/plugins/cmake/pack.py
cxx_flow/plugins/cmake/parser.py
cxx_flow/plugins/cmake/test.py
cxx_flow/plugins/commands/__init__.py
cxx_flow/plugins/commands/bootstrap.py
cxx_flow/plugins/commands/init.py
cxx_flow/plugins/commands/list.py
cxx_flow/plugins/commands/run.py
cxx_flow/plugins/commands/system.py
cxx_flow/plugins/commands/ci/__init__.py
cxx_flow/plugins/commands/ci/changelog.py
cxx_flow/plugins/commands/ci/matrix.py
cxx_flow/plugins/commands/ci/release.py
cxx_flow/plugins/conan/__init__.py
cxx_flow/plugins/conan/_conan.py
cxx_flow/plugins/sign/__init__.py
cxx_flow/plugins/sign/win32.py
cxx_flow/plugins/store/__init__.py
cxx_flow/plugins/store/store_both.py
cxx_flow/plugins/store/store_packages.py
cxx_flow/plugins/store/store_tests.py
cxx_flow-0.8.0.dist-info/METADATA
cxx_flow-0.8.0.dist-info/WHEEL
cxx_flow-0.8.0.dist-info/entry_points.txt
cxx_flow-0.8.0.dist-info/licenses/LICENSE
cxx_flow-0.8.0.dist-info/RECORD
