Metadata-Version: 2.4
Name: cxx-flow
Version: 0.8.0
Summary: C++ project maintenance, automated
Project-URL: Homepage, https://pypi.org/project/cxx-flow/
Project-URL: Source Code, https://github.com/mzdun/cxx-flow
Project-URL: Documentation, https://cxx-flow.readthedocs.io/en/latest/
Author-email: Marcin Zdun <marcin.zdun@gmail.com>
License-File: LICENSE
Keywords: C/C++,c++,ci,cpp,dependency,developer,manager,tool
Classifier: Development Status :: 4 - Beta
Classifier: Intended Audience :: Developers
Classifier: License :: OSI Approved :: MIT License
Classifier: Operating System :: OS Independent
Classifier: Programming Language :: Python :: 3
Classifier: Programming Language :: Python :: 3.10
Classifier: Topic :: Software Development :: Build Tools
Requires-Python: >=3.10
Requires-Dist: argcomplete
Requires-Dist: chevron2021
Requires-Dist: prompt-toolkit
Requires-Dist: pyyaml
